papermerge_cli/__init__.py
papermerge_cli/api_client.py
papermerge_cli/depricated_rest.py
papermerge_cli/exceptions.py
papermerge_cli/format/__init__.py
papermerge_cli/format/nodes.py
papermerge_cli/format/users.py
papermerge_cli/lib/__init__.py
papermerge_cli/lib/importer.py
papermerge_cli/lib/nodes.py
papermerge_cli/lib/users.py
papermerge_cli/lib/version.py
papermerge_cli/main.py
papermerge_cli/rest/__init__.py
papermerge_cli/rest/documents.py
papermerge_cli/rest/nodes.py
papermerge_cli/rest/users.py
papermerge_cli/rest/version.py
papermerge_cli/schema/__init__.py
papermerge_cli/schema/documents.py
papermerge_cli/schema/folders.py
papermerge_cli/schema/nodes.py
papermerge_cli/schema/paginator.py
papermerge_cli/schema/users.py
papermerge_cli/schema/version.py
papermerge_cli/types.py
papermerge_cli/utils.py
papermerge_cli-0.8.0.dist-info/LICENSE
papermerge_cli-0.8.0.dist-info/METADATA
papermerge_cli-0.8.0.dist-info/WHEEL
papermerge_cli-0.8.0.dist-info/entry_points.txt
papermerge_cli-0.8.0.dist-info/RECORD
