Metadata-Version: 2.1
Name: papermerge-cli
Version: 0.8.0
Summary: Command line utility for your Papermerge DMS instance
License: Apache 2.0
Author: Eugen Ciur
Author-email: eugen@papermerge.com
Requires-Python: >=3.10,<4.0
Classifier: License :: Other/Proprietary License
Classifier: Programming Language :: Python :: 3
Classifier: Programming Language :: Python :: 3.10
Classifier: Programming Language :: Python :: 3.11
Classifier: Programming Language :: Python :: 3.12
Requires-Dist: backoff (>=2.2.1,<3.0.0)
Requires-Dist: click (>=8.1.3,<9.0.0)
Requires-Dist: laconiq (>=0.3.0,<0.4.0)
Requires-Dist: pydantic[email] (>=2.5,<3.0)
Requires-Dist: requests (>=2.31.0,<3.0.0)
Requires-Dist: rich (>=13.4.2,<14.0.0)
Requires-Dist: typer[all] (>=0.9.0,<0.10.0)
